README.md
clc_inv.py
setup.py
clc_ansible_module/__init__.py
clc_ansible_module/clc_aa_policy.py
clc_ansible_module/clc_alert_policy.py
clc_ansible_module/clc_blueprint_package.py
clc_ansible_module/clc_firewall_policy.py
clc_ansible_module/clc_group.py
clc_ansible_module/clc_group_fact.py
clc_ansible_module/clc_loadbalancer.py
clc_ansible_module/clc_loadbalancer_fact.py
clc_ansible_module/clc_meta.py
clc_ansible_module/clc_meta_fact.py
clc_ansible_module/clc_modify_server.py
clc_ansible_module/clc_network.py
clc_ansible_module/clc_network_fact.py
clc_ansible_module/clc_publicip.py
clc_ansible_module/clc_server.py
clc_ansible_module/clc_server_fact.py
clc_ansible_module/clc_server_snapshot.py
clc_ansible_module.egg-info/PKG-INFO
clc_ansible_module.egg-info/SOURCES.txt
clc_ansible_module.egg-info/dependency_links.txt
clc_ansible_module.egg-info/requires.txt
clc_ansible_module.egg-info/top_level.txt