Metadata-Version: 1.1
Name: clc-ansible-module
Version: 1.1.26
Summary: Centurylink Cloud Ansible Modules
Home-page: https://github.com/CenturylinkCloud/clc-ansible-module
Author: CenturyLink Cloud
Author-email: cloudnativeservicesteam@lumen.com
License: UNKNOWN
Download-URL: https://github.com/CenturylinkCloud/clc-ansible-module.git
Keywords: centurylink cloud clc ansible modules
Platform: UNKNOWN
